{
  "id": "seoul-event-158072",
  "sourceId": "158072",
  "title": "[서울시립 백남준을 기억하는 집] 《메가트론 랩소디》 동기신호 프로그램, 프로토룸 [렉처퍼포먼스+렉처퍼포먼스 Matter Matters: 효율 너머의 코드와 데이터]",
  "category": "교육/체험",
  "district": "종로구",
  "venue": "서울시립 백남준을 기억하는 집(서울 종로구 종로53길 12-1)",
  "startDate": "2026-06-13",
  "endDate": "2026-06-13",
  "dateText": "2026-06-13~2026-06-13",
  "timeText": "15:00 ~ 17:00",
  "target": "누구나",
  "fee": "무료",
  "isFree": true,
  "organizer": "서울시립미술관",
  "inquiry": "홈페이지 참고",
  "imageUrl": "https://culture.seoul.go.kr/cmmn/file/getImage.do?atchFileId=6a73cdf5b316408b9f81eaa5c6818322&thumb=Y",
  "detailUrl": "https://culture.seoul.go.kr/culture/culture/cultureEvent/view.do?cultcode=158072&menuNo=200011",
  "summary": "종로구 · 서울시립 백남준을 기억하는 집(서울 종로구 종로53길 12-1)에서 열리는 교육/체험 행사입니다. 무료로 참여할 수 있는 행사입니다.",
  "organizerUrl": "https://sema.seoul.go.kr/kr/whatson/event/detail?evtNo=1544237",
  "ticketType": "기관",
  "description": "",
  "performer": "",
  "program": "",
  "latitude": 37.5730656233283,
  "longitude": 127.013775536144,
  "registeredAt": "2026-05-28",
  "collectedAt": "2026-06-04T22:56:50.168Z"
}