{
  "id": "seoul-event-157779",
  "sourceId": "157779",
  "title": "[앙상블 결 공연을 위한 어린이 클래스] w. 음악박사 스텔라",
  "category": "교육/체험",
  "district": "서초구",
  "venue": "라율아트홀",
  "startDate": "2026-05-10",
  "endDate": "2026-05-31",
  "dateText": "2026-05-10~2026-05-31",
  "timeText": "일요일 17:00 ~ 17:50",
  "target": "미취학 ~ 초등학생",
  "fee": "1회 65,000원 | 3회 112,000원",
  "isFree": false,
  "organizer": "기타",
  "inquiry": "02-522-7278",
  "imageUrl": "https://culture.seoul.go.kr/cmmn/file/getImage.do?atchFileId=8bd1b3ca7d3c414d81f766f460c66a7b&thumb=Y",
  "detailUrl": "https://culture.seoul.go.kr/culture/culture/cultureEvent/view.do?cultcode=157779&menuNo=200011",
  "summary": "서초구 · 라율아트홀에서 열리는 교육/체험 행사입니다. 1회 65,000원 | 3회 112,000원",
  "organizerUrl": "https://www.rayularthall.com/concerts/?q=YToxOntzOjEyOiJrZXl3b3JkX3R5cGUiO3M6MzoiYWxsIjt9&bmode=view&idx=171049041&t=board",
  "ticketType": "시민",
  "description": "",
  "performer": "",
  "program": "",
  "latitude": 37.4824452369632,
  "longitude": 127.012614908746,
  "registeredAt": "2026-05-07",
  "collectedAt": "2026-05-20T22:58:33.687Z"
}