{
  "id": "seoul-event-158128",
  "sourceId": "158128",
  "title": "[서울아트책보고] 처음 만나는 동시대 미술 - 이소영 미술 에세이스트",
  "category": "교육/체험",
  "district": "구로구",
  "venue": "서울아트책보고 워크숍룸",
  "startDate": "2026-06-17",
  "endDate": "2026-07-01",
  "dateText": "2026-06-17~2026-07-01",
  "timeText": " 10:30 ~ 12:30",
  "target": "성인 누구나",
  "fee": "무료",
  "isFree": true,
  "organizer": "서울아트책보고",
  "inquiry": "02-2066-4839",
  "imageUrl": "https://culture.seoul.go.kr/cmmn/file/getImage.do?atchFileId=670bf276b9a145b0844c6bbf6b4bd901&thumb=Y",
  "detailUrl": "https://culture.seoul.go.kr/culture/culture/cultureEvent/view.do?cultcode=158128&menuNo=200011",
  "summary": "구로구 · 서울아트책보고 워크숍룸에서 열리는 교육/체험 행사입니다. 무료로 참여할 수 있는 행사입니다.",
  "organizerUrl": "https://artbookbogo.kr/seoul/menu/10024/program/30009/cultureDetail.do?currentPageNo=1&cultureIdx=24782&cultureTypeCdArr=EDUC&searchCultureTypeCd=&searchOperStatusCd=VALID",
  "ticketType": "기관",
  "description": "",
  "performer": "",
  "program": "",
  "latitude": 37.4982125677913,
  "longitude": 126.867088741096,
  "registeredAt": "2026-06-04",
  "collectedAt": "2026-06-05T22:52:04.386Z"
}