{
  "id": "seoul-event-158633",
  "sourceId": "158633",
  "title": "마에스트로 핑고와 떠나는 클래식 지구 한 바퀴",
  "category": "클래식",
  "district": "서초구",
  "venue": "서울체임버홀",
  "startDate": "2026-08-08",
  "endDate": "2026-08-09",
  "dateText": "2026-08-08~2026-08-09",
  "timeText": "토, 일요일 13:00, 16:00",
  "target": "만3세 이상 누구나!",
  "fee": "30,000원",
  "isFree": false,
  "organizer": "기타",
  "inquiry": "070-8811-0513",
  "imageUrl": "https://culture.seoul.go.kr/cmmn/file/getImage.do?atchFileId=40b1800588514d9fb7bb1c936f0d1728&thumb=Y",
  "detailUrl": "https://culture.seoul.go.kr/culture/culture/cultureEvent/view.do?cultcode=158633&menuNo=200008",
  "summary": "서초구 · 서울체임버홀에서 열리는 클래식 행사입니다. 30,000원",
  "organizerUrl": "http://gaonclassic.com/bbs/bbs/view.php?bbs_no=11&data_no=336&page_no=1&sub_id=",
  "ticketType": "시민",
  "description": "",
  "performer": "피아노, 바이올린, 첼로, 플루트, 클라리넷과 타악기 까지!",
  "program": "비제의 「카르멘 환상곡」부터 브람스, 쇼팽, 비발디, 오펜바흐, 엘가, 피아졸라, 그리그, 요한 슈트라우스 그리고 디즈니 메들리까지! 아이들과 어른들 모두 즐거운 클래식 공연",
  "latitude": 37.5047177127649,
  "longitude": 126.998308072811,
  "registeredAt": "2026-07-13",
  "collectedAt": "2026-07-17T23:26:10.428Z"
}