{
  "id": "seoul-event-158064",
  "sourceId": "158064",
  "title": "더 아카이브: 뮤지컬의 순간들",
  "category": "콘서트",
  "district": "용산구",
  "venue": "국립중앙박물관 극장 용  ",
  "startDate": "2026-06-27",
  "endDate": "2026-06-28",
  "dateText": "2026-06-27~2026-06-28",
  "timeText": "17:00",
  "target": "초등학생 이상",
  "fee": "R석 8만원 S석 5만원",
  "isFree": false,
  "organizer": "기타",
  "inquiry": "1544-5955",
  "imageUrl": "https://culture.seoul.go.kr/cmmn/file/getImage.do?atchFileId=a3f308fab6c1405c942a53078c77caee&thumb=Y",
  "detailUrl": "https://culture.seoul.go.kr/culture/culture/cultureEvent/view.do?cultcode=158064&menuNo=200008",
  "summary": "용산구 · 국립중앙박물관 극장 용  에서 열리는 콘서트 행사입니다. R석 8만원 S석 5만원",
  "organizerUrl": "https://www.nmf.or.kr/user/performance/plan_view.do?show_id=S20260430160755925100&page=1",
  "ticketType": "기관",
  "description": "",
  "performer": "예술감독 양준모, 강필석, 김승대, 린아, 이충주, 존 아이젠, 정욱진, 이아름솔, 설가은 등 ",
  "program": "무대 위에서 빛났던 명장면과 배우들의 순간들이 하나의 아카이브로 기록되어 관객 여러분을 찾아갑니다.",
  "latitude": 37.5247022357875,
  "longitude": 126.977740246542,
  "registeredAt": "2026-05-28",
  "collectedAt": "2026-06-11T23:05:08.804Z"
}