{
  "id": "seoul-event-157073",
  "sourceId": "157073",
  "title": "[영등포문화재단] 2026 도림 생활문화센터 특별프로그램",
  "category": "교육/체험",
  "district": "영등포구",
  "venue": "도림 생활문화센터(영등포구 도신로 33길 4)",
  "startDate": "2026-04-02",
  "endDate": "2026-07-21",
  "dateText": "2026-04-02~2026-07-21",
  "timeText": "시니어 모델: 매주 (화) 14:00~15:40 / 성우 입체낭독: 매주 (목) 19:00~21:00",
  "target": "시니어 모델: 50대 이상 / 성우 입체낭독: 12세 이상",
  "fee": "시니어 모델: 참여비 100,000원 / 성우 입체낭독: 참여비 70,000원",
  "isFree": false,
  "organizer": "영등포문화재단",
  "inquiry": "02-846-2983",
  "imageUrl": "https://culture.seoul.go.kr/cmmn/file/getImage.do?atchFileId=71ba9d5a073c49deb4051fb19a843254&thumb=Y",
  "detailUrl": "https://culture.seoul.go.kr/culture/culture/cultureEvent/view.do?cultcode=157073&menuNo=200011",
  "summary": "영등포구 · 도림 생활문화센터(영등포구 도신로 33길 4)에서 열리는 교육/체험 행사입니다. 시니어 모델: 참여비 100,000원 / 성우 입체낭독: 참여비 70,000원",
  "organizerUrl": "https://www.ydpcf.or.kr/artexhibit/view.do?id=530",
  "ticketType": "기관",
  "description": "",
  "performer": "",
  "program": "",
  "latitude": 37.5099911988676,
  "longitude": 126.908050531966,
  "registeredAt": "2026-03-17",
  "collectedAt": "2026-04-27T22:50:02.820Z"
}