{
  "id": "seoul-event-157326",
  "sourceId": "157326",
  "title": "[구립증산도서관] 도서관의 날 기념 [팔랑팔랑 벚꽃 북크닉]",
  "category": "교육/체험",
  "district": "은평구",
  "venue": "지하 문화강좌실 및 불광천",
  "startDate": "2026-04-12",
  "endDate": "2026-04-12",
  "dateText": "2026-04-12~2026-04-12",
  "timeText": "10:30 ~ 12:00",
  "target": "6~8세 아동 10명",
  "fee": "무료",
  "isFree": true,
  "organizer": "은평구청",
  "inquiry": "02-307-6030",
  "imageUrl": "https://culture.seoul.go.kr/cmmn/file/getImage.do?atchFileId=5169ba0a181f4aad96ca528ec315ed40&thumb=Y",
  "detailUrl": "https://culture.seoul.go.kr/culture/culture/cultureEvent/view.do?cultcode=157326&menuNo=200011",
  "summary": "은평구 · 지하 문화강좌실 및 불광천에서 열리는 교육/체험 행사입니다. 무료로 참여할 수 있는 행사입니다.",
  "organizerUrl": "https://www.jsplib.or.kr/culture/event.asp?mode=view&lecture_seq=2301&listname=normal",
  "ticketType": "기관",
  "description": "",
  "performer": "",
  "program": "",
  "latitude": 37.5828094398328,
  "longitude": 126.907671330325,
  "registeredAt": "2026-04-06",
  "collectedAt": "2026-04-13T22:48:41.788Z"
}