{
  "id": "seoul-event-157776",
  "sourceId": "157776",
  "title": "[미래한강본부] 2026 한강 서래섬 피크닉 콘서트 [봄결찬란]",
  "category": "콘서트",
  "district": "서초구",
  "venue": "반포한강공원 서래섬",
  "startDate": "2026-05-08",
  "endDate": "2026-05-10",
  "dateText": "2026-05-08~2026-05-10",
  "timeText": "14:00 ~ 20:00",
  "target": "누구나 자유롭게 참여 가능",
  "fee": "무료",
  "isFree": true,
  "organizer": "미래한강본부",
  "inquiry": "홈페이지 참고",
  "imageUrl": "https://culture.seoul.go.kr/cmmn/file/getImage.do?atchFileId=d5a70a02d66147888408d575008be5bf&thumb=Y",
  "detailUrl": "https://culture.seoul.go.kr/culture/culture/cultureEvent/view.do?cultcode=157776&menuNo=200008",
  "summary": "서초구 · 반포한강공원 서래섬에서 열리는 콘서트 행사입니다. 무료로 참여할 수 있는 행사입니다.",
  "organizerUrl": "https://hangang.seoul.go.kr/www/eventMng/detail.do?srchType=list&evntSn=405&mid=538&pageNo=3&keyword=&opt4=&opt11=&opt12=&opt13=&opt14=#pstnList",
  "ticketType": "기관",
  "description": "",
  "performer": "",
  "program": "",
  "latitude": 37.5097694752014,
  "longitude": 126.995269636407,
  "registeredAt": "2026-05-07",
  "collectedAt": "2026-05-13T22:52:46.890Z"
}