{
  "id": "seoul-event-158083",
  "sourceId": "158083",
  "title": "[서울무형유산교육전시장] 2026년 달빛공방 모집 안내",
  "category": "교육/체험",
  "district": "종로구",
  "venue": "서울무형유산교육전시장(서울시 종로구 율곡로10길 13)",
  "startDate": "2026-06-10",
  "endDate": "2026-07-03",
  "dateText": "2026-06-10~2026-07-03",
  "timeText": "매주 수, 금요일 19:00~21:00(4주간 4회 참여)",
  "target": "만 19세 이상",
  "fee": "재료비 30,000원",
  "isFree": false,
  "organizer": "서울무형유산교육전시장",
  "inquiry": "02-742-6444",
  "imageUrl": "https://culture.seoul.go.kr/cmmn/file/getImage.do?atchFileId=d63c9970fac84f96a7e3175a956fdbca&thumb=Y",
  "detailUrl": "https://culture.seoul.go.kr/culture/culture/cultureEvent/view.do?cultcode=158083&menuNo=200011",
  "summary": "종로구 · 서울무형유산교육전시장(서울시 종로구 율곡로10길 13)에서 열리는 교육/체험 행사입니다. 재료비 30,000원",
  "organizerUrl": "https://seoulmaster.co.kr/bbs/board.php?bo_table=bbs1&wr_id=217",
  "ticketType": "기관",
  "description": "",
  "performer": "",
  "program": "",
  "latitude": 37.5769351431409,
  "longitude": 126.991104508988,
  "registeredAt": "2026-05-29",
  "collectedAt": "2026-06-08T23:01:41.063Z"
}