{
  "id": "seoul-food-3160000-101-2019-00378",
  "sourceId": "3160000-101-2019-00378",
  "name": "드림푸드",
  "district": "구로구",
  "area": "구로동",
  "category": "한식",
  "mainMenu": "한식",
  "address": "서울특별시 구로구 구로동 237 지하이시티 지하1층 B114, B115호",
  "roadAddress": "서울특별시 구로구 디지털로 243, 지하이시티 지하1층 B114, B115호 (구로동)",
  "phone": "",
  "status": "영업",
  "detailStatus": "영업",
  "licenseDate": "2019-11-28",
  "closedDate": "",
  "updatedAt": "2026-05-01",
  "sourceLabel": "서울 열린데이터광장 일반음식점 인허가 정보",
  "sourceUrl": "https://data.seoul.go.kr/dataList/OA-16094/S/1/datasetView.do",
  "collectedAt": "2026-05-03T22:48:50.713Z",
  "mapSearchQuery": "서울특별시 구로구 디지털로 243",
  "latitude": null,
  "longitude": null,
  "x": 190402.032127103,
  "y": 442203.137447127,
  "summary": "구로구 구로동에 등록된 한식 일반음식점입니다. 영업시간, 휴무, 메뉴는 방문 전 지도 또는 공식 채널에서 다시 확인해 주세요."
}