{
  "id": "seoul-food-3060000-101-2026-00094",
  "sourceId": "3060000-101-2026-00094",
  "name": "잉어와 잔치국수",
  "district": "중랑구",
  "area": "면목동",
  "category": "분식",
  "mainMenu": "분식",
  "address": "서울특별시 중랑구 면목동 181-126 만덕어린이집",
  "roadAddress": "서울특별시 중랑구 동일로101길 32, 만덕어린이집 1층 (면목동)",
  "phone": "",
  "status": "영업",
  "detailStatus": "영업",
  "licenseDate": "2026-04-27",
  "closedDate": "",
  "updatedAt": "2026-04-28",
  "sourceLabel": "서울 열린데이터광장 일반음식점 인허가 정보",
  "sourceUrl": "https://data.seoul.go.kr/dataList/OA-16094/S/1/datasetView.do",
  "collectedAt": "2026-04-29T08:14:27.671Z",
  "mapSearchQuery": "서울특별시 중랑구 동일로101길 32",
  "latitude": null,
  "longitude": null,
  "x": 206824.839835749,
  "y": 454090.598177366,
  "summary": "중랑구 면목동에 등록된 분식 일반음식점입니다. 영업시간, 휴무, 메뉴는 방문 전 지도 또는 공식 채널에서 다시 확인해 주세요."
}