{
  "id": "seoul-food-3110000-101-2023-00215",
  "sourceId": "3110000-101-2023-00215",
  "name": "호코 연신내본점",
  "district": "은평구",
  "area": "갈현동",
  "category": "경양식",
  "mainMenu": "경양식",
  "address": "서울특별시 은평구 갈현동 110-41 2층",
  "roadAddress": "서울특별시 은평구 연서로27길 21, 2층 (갈현동)",
  "phone": "",
  "status": "영업",
  "detailStatus": "영업",
  "licenseDate": "2023-05-26",
  "closedDate": "",
  "updatedAt": "2026-04-28",
  "sourceLabel": "서울 열린데이터광장 일반음식점 인허가 정보",
  "sourceUrl": "https://data.seoul.go.kr/dataList/OA-16094/S/1/datasetView.do",
  "collectedAt": "2026-04-29T22:51:06.140Z",
  "mapSearchQuery": "서울특별시 은평구 연서로27길 21",
  "latitude": null,
  "longitude": null,
  "x": 192610.04228242,
  "y": 457329.396681059,
  "summary": "은평구 갈현동에 등록된 경양식 일반음식점입니다. 영업시간, 휴무, 메뉴는 방문 전 지도 또는 공식 채널에서 다시 확인해 주세요."
}