{
  "id": "seoul-food-3180000-101-2020-00666",
  "sourceId": "3180000-101-2020-00666",
  "name": "우마이덮밥",
  "district": "영등포구",
  "area": "여의도동",
  "category": "일식",
  "mainMenu": "일식",
  "address": "서울특별시 영등포구 여의도동 44-12 고려빌딩",
  "roadAddress": "서울특별시 영등포구 여의대방로67길 8, 고려빌딩 205호 (여의도동)",
  "phone": "",
  "status": "영업",
  "detailStatus": "영업",
  "licenseDate": "2020-06-02",
  "closedDate": "",
  "updatedAt": "2026-04-29",
  "sourceLabel": "서울 열린데이터광장 일반음식점 인허가 정보",
  "sourceUrl": "https://data.seoul.go.kr/dataList/OA-16094/S/1/datasetView.do",
  "collectedAt": "2026-05-01T22:49:37.393Z",
  "mapSearchQuery": "서울특별시 영등포구 여의대방로67길 8",
  "latitude": null,
  "longitude": null,
  "x": 193839.302798329,
  "y": 446370.230571887,
  "summary": "영등포구 여의도동에 등록된 일식 일반음식점입니다. 영업시간, 휴무, 메뉴는 방문 전 지도 또는 공식 채널에서 다시 확인해 주세요."
}