{
  "id": "seoul-food-3170000-101-2017-00121",
  "sourceId": "3170000-101-2017-00121",
  "name": "각시보쌈 가산디지털점",
  "district": "금천구",
  "area": "가산동",
  "category": "냉면집",
  "mainMenu": "냉면집",
  "address": "서울특별시 금천구 가산동 481-11 대륭테크노타운8차 지상1층 112호",
  "roadAddress": "서울특별시 금천구 가마산로 96, 지상1층 112호 (가산동, 대륭테크노타운8차)",
  "phone": "",
  "status": "영업",
  "detailStatus": "영업",
  "licenseDate": "2017-06-29",
  "closedDate": "",
  "updatedAt": "2026-04-25",
  "sourceLabel": "서울 열린데이터광장 일반음식점 인허가 정보",
  "sourceUrl": "https://data.seoul.go.kr/dataList/OA-16094/S/1/datasetView.do",
  "collectedAt": "2026-04-29T22:51:06.140Z",
  "mapSearchQuery": "서울특별시 금천구 가마산로 96",
  "latitude": null,
  "longitude": null,
  "x": 189089.927764903,
  "y": 442569.300676147,
  "summary": "금천구 가산동에 등록된 냉면집 일반음식점입니다. 영업시간, 휴무, 메뉴는 방문 전 지도 또는 공식 채널에서 다시 확인해 주세요."
}