{
  "id": "seoul-food-3040000-101-2025-00468",
  "sourceId": "3040000-101-2025-00468",
  "name": "제니샤브",
  "district": "광진구",
  "area": "화양동",
  "category": "한식",
  "mainMenu": "한식",
  "address": "서울특별시 광진구 화양동 12-39",
  "roadAddress": "서울특별시 광진구 능동로13길 44, 1층 (화양동)",
  "phone": "",
  "status": "영업",
  "detailStatus": "영업",
  "licenseDate": "2025-12-11",
  "closedDate": "",
  "updatedAt": "2026-05-02",
  "sourceLabel": "서울 열린데이터광장 일반음식점 인허가 정보",
  "sourceUrl": "https://data.seoul.go.kr/dataList/OA-16094/S/1/datasetView.do",
  "collectedAt": "2026-05-04T22:50:42.971Z",
  "mapSearchQuery": "서울특별시 광진구 능동로13길 44",
  "latitude": null,
  "longitude": null,
  "x": 206127.412962608,
  "y": 449074.563932226,
  "summary": "광진구 화양동에 등록된 한식 일반음식점입니다. 영업시간, 휴무, 메뉴는 방문 전 지도 또는 공식 채널에서 다시 확인해 주세요."
}