{
  "id": "gov-benefit-O00023200001",
  "sourceId": "O00023200001",
  "title": "동작구 핫둘핫둘서울 유아 스포츠단",
  "field": "보육·교육",
  "provider": "동작구시설관리공단",
  "providerType": "자치구",
  "district": "동작구",
  "userType": "법인/시설/단체",
  "deadlineText": "상시신청",
  "deadlineSortKey": "9999-12-31",
  "isAlwaysOpen": true,
  "targetSummary": "유아스포츠단에 참여를 희망하는 관내 어린이집(만3세~5세)",
  "summary": "동작구시설관리공단에서 제공하는 보육·교육 혜택입니다. 유아스포츠단을 지속 운영하여 성인 대비 스포츠 활동에 취약한 유아들이 건강하게 자랄 수 있도록 평생 생활체육 기반을 마련하고자 함",
  "supportType": "기타(교육)",
  "supportSummary": "○ 관내 어린이집(만3세~5세) 대상 유아스포츠단 프로그램 제공\n\n○ 프로그램 내용\n - 체육시설과 어린이집을 연계하여 유아의 정기적 체육활동 프로세서를 구축‧운영하는 유아 스포츠단 운영",
  "receptionAgency": "접수기관 정보 없음",
  "applicationMethodTypes": [
    "방문신청",
    "직접입력"
  ],
  "detailUrl": "https://www.gov.kr/portal/rcvfvrSvc/dtlEx/O00023200001",
  "onlineUrl": "",
  "inquiry": [
    "동작구청 체육정책과 생활체육팀/02-820-9439",
    "동작구시설관리공단 체육사업팀/070-7204-3974"
  ],
  "updatedAt": "2026-01-30",
  "registeredAt": "2022-07-15",
  "viewCount": 664,
  "collectedAt": "2026-04-21T22:47:57.014Z",
  "purpose": "유아스포츠단을 지속 운영하여 성인 대비 스포츠 활동에 취약한 유아들이 건강하게 자랄 수 있도록 평생 생활체육 기반을 마련하고자 함",
  "target": "유아스포츠단에 참여를 희망하는 관내 어린이집(만3세~5세)",
  "selectionCriteria": "",
  "supportContent": "○ 관내 어린이집(만3세~5세) 대상 유아스포츠단 프로그램 제공\n\n○ 프로그램 내용\n - 체육시설과 어린이집을 연계하여 유아의 정기적 체육활동 프로세서를 구축‧운영하는 유아 스포츠단 운영",
  "applicationMethod": "○ 방문 신청\n\n○ 전화신청 : 동작구청 체육정책과 생활체육팀 / 02-820-9439",
  "documents": "해당없음",
  "officialDocuments": "해당없음",
  "identityDocuments": "해당없음",
  "legalBasis": [],
  "ordinance": "서울특별시 체육진흥 조례(제16조)",
  "inquiryText": "동작구청 체육정책과 생활체육팀/02-820-9439||동작구시설관리공단 체육사업팀/070-7204-3974",
  "ageMin": 0,
  "ageMax": 0
}