{
  "id": "gov-benefit-611000019598",
  "sourceId": "611000019598",
  "title": "주택용 소방시설(주택화재경보기, 소화기) 보급 및 설치 지원",
  "field": "생활안정",
  "provider": "서울특별시",
  "providerType": "서울시",
  "district": "서울특별시",
  "userType": "가구",
  "deadlineText": "상시신청",
  "deadlineSortKey": "9999-12-31",
  "isAlwaysOpen": true,
  "targetSummary": "○ 서울특별시 주택의 소방시설 설치 조례 제3조(주택용 소방시설의 우선 설치대상) \n    1.「노인복지법」에 따른 노인이 홀로 거주하는 주택\n    2.「장애인복지법」에 따른 장애인 또는 지체부자유자가 거주하는 주택\n    3.  소년소녀가장, 한부모 가정 주택…",
  "summary": "서울특별시에서 제공하는 생활안정 혜택입니다. 기초생활수급자, 홀몸어르신, 지하층거주자, 장애인 등 취약계층을 대상으로 주택용 소방시설(주택화재경보기, 소화기)을 보급하여 주택화재 인명피해를 최소화 하고자 함",
  "supportType": "현물",
  "supportSummary": "사업기간 : 연중지속\n사업내용 : 취약계층 주택용 소방시설(주택화재경보기, 소화기) 보급 및 설치 지원\n사업수행주체 : 25개 소방관서",
  "receptionAgency": "접수기관 정보 없음",
  "applicationMethodTypes": [
    "기타 온라인신청",
    "방문신청"
  ],
  "detailUrl": "https://www.gov.kr/portal/rcvfvrSvc/dtlEx/611000019598",
  "onlineUrl": "https://fire.seoul.go.kr/pages/cnts.do?id=4808",
  "inquiry": [
    "서울소방재난본부 예방과 예방팀/02-3706-1516"
  ],
  "updatedAt": "2026-02-23",
  "registeredAt": "2023-10-19",
  "viewCount": 2288,
  "collectedAt": "2026-04-29T22:50:48.682Z",
  "purpose": "기초생활수급자, 홀몸어르신, 지하층거주자, 장애인 등 취약계층을 대상으로 주택용 소방시설(주택화재경보기, 소화기)을 보급하여 주택화재 인명피해를 최소화 하고자 함",
  "target": "○ 서울특별시 주택의 소방시설 설치 조례 제3조(주택용 소방시설의 우선 설치대상) \n    1.「노인복지법」에 따른 노인이 홀로 거주하는 주택\n    2.「장애인복지법」에 따른 장애인 또는 지체부자유자가 거주하는 주택\n    3.  소년소녀가장, 한부모 가정 주택\n    4.「국민기초생활보장법」에 따른 국민기초생활수급자가 거주하는 주택\n         (차상위계층 포함)\n    5.「다문화가족지원법」에 따른 다문화 가족이 거주하는 주택\n    6.「건축법」에 따른 지하층을 거주 목적으로 사용하는 주택\n    7. 소방차 통행이 곤란한 지역에 위치한 주택\n    8. 화재예방강화지구 접경 20미터 이내에 위치한 주택",
  "selectionCriteria": "",
  "supportContent": "사업기간 : 연중지속\n사업내용 : 취약계층 주택용 소방시설(주택화재경보기, 소화기) 보급 및 설치 지원\n사업수행주체 : 25개 소방관서",
  "applicationMethod": "○ 온라인 신청 : 서울소방재난본부 홈페이지\n   - https://fire.seoul.go.kr/pages/cnts.do?id=4808\n○ 방문 : 관할소방서 예방과 예방팀\n○ 유선 : 관할소방서 예방과 예방팀",
  "documents": "해당없음",
  "officialDocuments": "해당없음",
  "identityDocuments": "해당없음",
  "legalBasis": [
    "소방시설 설치 및 관리에 관한 법률(제10조, 제1항)",
    "소방시설 설치 및 관리에 관한 법률(제10조, 제2항)",
    "소방시설 설치 및 관리에 관한 법률(제10조, 제3항)"
  ],
  "ordinance": "서울특별시 주택의 소방시설 설치 조례(제3조)",
  "inquiryText": "서울소방재난본부 예방과 예방팀/02-3706-1516",
  "ageMin": 1,
  "ageMax": 120
}