{
  "id": "gov-benefit-310000000120",
  "sourceId": "310000000120",
  "title": "국가유공자 위문 지원",
  "field": "생활안정",
  "provider": "서울특별시 노원구",
  "providerType": "자치구",
  "district": "노원구",
  "userType": "개인",
  "deadlineText": "상시신청",
  "deadlineSortKey": "9999-12-31",
  "isAlwaysOpen": true,
  "targetSummary": "○ 국가보훈대상자 및 수권유족\n○ 유족승계를 받지 못한 사망한 참전유공자 배우자",
  "summary": "서울특별시 노원구에서 제공하는 생활안정 혜택입니다. 국가를 위하여 헌신한 국가보훈대상자의 희생을 기억하고 예우와 지원을 강화하기 위하여 노원구 보훈예우수당, 참전유공자 배우자 복지수당 및 보훈명절위문금, 사망위로금을 지급하고자 함",
  "supportType": "현금",
  "supportSummary": "○ 국가유공자 본인 및 수권유족에 사망위로금, 보훈예우수당, 보훈명절위문금 지급\n○ 유족승계를 받지 못한 사망한 참전유공자 배우자에게 배우자 복지수당 지급",
  "receptionAgency": "접수기관 정보 없음",
  "applicationMethodTypes": [
    "방문신청"
  ],
  "detailUrl": "https://www.gov.kr/portal/rcvfvrSvc/dtlEx/310000000120",
  "onlineUrl": "",
  "inquiry": [
    "주민복지정책과/02-2116-3652"
  ],
  "updatedAt": "2026-04-24",
  "registeredAt": "2021-09-23",
  "viewCount": 1138,
  "collectedAt": "2026-04-24T22:47:58.372Z",
  "purpose": "국가를 위하여 헌신한 국가보훈대상자의 희생을 기억하고 예우와 지원을 강화하기 위하여 노원구 보훈예우수당, 참전유공자 배우자 복지수당 및 보훈명절위문금, 사망위로금을 지급하고자 함",
  "target": "○ 국가보훈대상자 및 수권유족\n○ 유족승계를 받지 못한 사망한 참전유공자 배우자",
  "selectionCriteria": "",
  "supportContent": "○ 국가유공자 본인 및 수권유족에 사망위로금, 보훈예우수당, 보훈명절위문금 지급\n○ 유족승계를 받지 못한 사망한 참전유공자 배우자에게 배우자 복지수당 지급",
  "applicationMethod": "○ 신청방법 : 동 주민센터로 노원구보훈예우수당, 사망위로금, 참전유공자 배우자 복지수당 신청\n\n○ 지급시기 및 지급방법\n    - 지급개시일 : 신청월을 수당지급 개시일로 함(단, 전입자는 신청월 전거주지 지급여부 확인후 미지급시 지급)\n    - 지급방법 : 수급자 계좌에 직접 입금",
  "documents": "○ 신청인 제출서류\n  - 국가보훈대상자등록증(유족증,유공자증) 또는 참전유공자 확인서\n  - 통장사본\n  - 가족관계증명서(사망위로금, 참전유공자 배우자 복지수당 신청시)\n  - 말소자 초본(참전유공자 배우자 복지수당 신청시)",
  "officialDocuments": "해당없음",
  "identityDocuments": "해당없음",
  "legalBasis": [],
  "ordinance": "서울특별시 노원구 국가보훈대상자 예우 및 지원에 관한 조례",
  "inquiryText": "주민복지정책과/02-2116-3652",
  "ageMin": 0,
  "ageMax": 120
}