{
  "id": "gov-benefit-314000000101",
  "sourceId": "314000000101",
  "title": "효도수당",
  "field": "보호·돌봄",
  "provider": "서울특별시 양천구",
  "providerType": "자치구",
  "district": "양천구",
  "userType": "가구",
  "deadlineText": "상시신청",
  "deadlineSortKey": "9999-12-31",
  "isAlwaysOpen": true,
  "targetSummary": "○ 양천구에 실제 거주하고 주민등록이 되어 있는 만100세 이상의 부모 등을 부양하고 있는 가정의 세대주 또는 가족대표",
  "summary": "서울특별시 양천구에서 제공하는 보호·돌봄 혜택입니다. 100세 이상 부모 등을 부양하고 있는 가정에 효도수당 지급",
  "supportType": "현금",
  "supportSummary": "○ 세대당 연 20만원 1회 지급",
  "receptionAgency": "접수기관 정보 없음",
  "applicationMethodTypes": [
    "정부24온라인신청",
    "방문신청"
  ],
  "detailUrl": "https://www.gov.kr/portal/rcvfvrSvc/dtlEx/314000000101",
  "onlineUrl": "",
  "inquiry": [
    "어르신복지과/02-2620-3359"
  ],
  "updatedAt": "2026-01-30",
  "registeredAt": "2021-09-23",
  "viewCount": 1514,
  "collectedAt": "2026-04-28T22:50:26.294Z",
  "purpose": "100세 이상 부모 등을 부양하고 있는 가정에 효도수당 지급",
  "target": "○ 양천구에 실제 거주하고 주민등록이 되어 있는 만100세 이상의 부모 등을 부양하고 있는 가정의 세대주 또는 가족대표",
  "selectionCriteria": "",
  "supportContent": "○ 세대당 연 20만원 1회 지급",
  "applicationMethod": "○ 방문 신청\n - 주민센터 : 동주민센터 접수 신청",
  "documents": "- 효도수당 신청서\n- 신분증\n- 통장사본",
  "officialDocuments": "해당없음",
  "identityDocuments": "- 주민등록등본\n- 가족관계증명서",
  "legalBasis": [],
  "ordinance": "서울특별시 양천구 효행 장려 및 지원에 관한 조례",
  "inquiryText": "어르신복지과/02-2620-3359",
  "ageMin": 100,
  "ageMax": 120
}