{
  "id": "gov-benefit-611000000154",
  "sourceId": "611000000154",
  "title": "일본군 위안부 피해자 생활보조금 등 지원",
  "field": "보호·돌봄",
  "provider": "서울특별시",
  "providerType": "서울시",
  "district": "서울특별시",
  "userType": "개인",
  "deadlineText": "상시신청",
  "deadlineSortKey": "9999-12-31",
  "isAlwaysOpen": true,
  "targetSummary": "○ 일본군 '위안부' 피해자 등록자(여성가족부) 중 서울시 거주자",
  "summary": "서울특별시에서 제공하는 보호·돌봄 혜택입니다. 일본군 위안부 피해자를 대상으로 생활보조금 및 건강관리비 지원",
  "supportType": "현금",
  "supportSummary": "○ 여성가족부에 등록된 서울시 거주 일본군 '위안부' 피해자 대상 생활보조금 및 건강관리비 지원",
  "receptionAgency": "접수기관 정보 없음",
  "applicationMethodTypes": [
    "신청불필요"
  ],
  "detailUrl": "https://www.gov.kr/portal/rcvfvrSvc/dtlEx/611000000154",
  "onlineUrl": "",
  "inquiry": [
    "다산콜센터/02-120",
    "양성평등담당관/02-2133-5326"
  ],
  "updatedAt": "2026-02-02",
  "registeredAt": "2021-09-23",
  "viewCount": 767,
  "collectedAt": "2026-04-22T22:49:06.969Z",
  "purpose": "일본군 위안부 피해자를 대상으로 생활보조금 및 건강관리비 지원",
  "target": "○ 일본군 '위안부' 피해자 등록자(여성가족부) 중 서울시 거주자",
  "selectionCriteria": "",
  "supportContent": "○ 여성가족부에 등록된 서울시 거주 일본군 '위안부' 피해자 대상 생활보조금 및 건강관리비 지원",
  "applicationMethod": "○ 개인 신청절차 없음",
  "documents": "해당없음",
  "officialDocuments": "해당없음",
  "identityDocuments": "해당없음",
  "legalBasis": [],
  "ordinance": "서울특별시 일제하 일본군 위안부 피해자 지원 및 기념사업에 관한 조례",
  "inquiryText": "다산콜센터/02-120||양성평등담당관/02-2133-5326",
  "ageMin": 80,
  "ageMax": 120
}